nestipy_config/__init__.py
nestipy_config/config_builder.py
nestipy_config/config_module.py
nestipy_config/config_service.py
nestipy_config-0.1.6.dist-info/LICENSE
nestipy_config-0.1.6.dist-info/METADATA
nestipy_config-0.1.6.dist-info/WHEEL
nestipy_config-0.1.6.dist-info/RECORD
